cuequivariance_ops_torch_cu11-0.5.1.dist-info/METADATA
cuequivariance_ops_torch_cu11-0.5.1.dist-info/RECORD
cuequivariance_ops_torch_cu11-0.5.1.dist-info/WHEEL
cuequivariance_ops_torch_cu11-0.5.1.dist-info/licenses/LICENSE
cuequivariance_ops_torch/tensor_product_uniform_1d.py
cuequivariance_ops_torch/fused_tensor_product.py
cuequivariance_ops_torch/tensorrt.py
cuequivariance_ops_torch/segmented_transpose.py
cuequivariance_ops_torch/tensor_product_uniform_1d_jit.py
cuequivariance_ops_torch/utils.py
cuequivariance_ops_torch/__init__.py
cuequivariance_ops_torch/onnx.py
cuequivariance_ops_torch/triangle_attention.py
cuequivariance_ops_torch/symmetric_tensor_contraction.py
cuequivariance_ops_torch/tensor_product_uniform_1d_indexed.py
cuequivariance_ops_torch/fused_layer_norm_torch.py
cuequivariance_ops_torch/VERSION
cuequivariance_ops_torch/gated_gemm_torch.py
cuequivariance_ops_torch/_version.py
cuequivariance_ops_torch/triangle_multiplicative_update.py
cuequivariance_ops_torch/_ext/__init__.py
cuequivariance_ops_torch/_ext/cuequivariance_ops_torch_ext.cpython-311-x86_64-linux-gnu.so
