Metadata-Version: 2.1
Name: cuequivariance-ops-torch-cu11
Version: 0.5.1
Summary: cuequivariance-ops-torch - GPU Accelerated Torch Extensions for Equivariant Primitives
Author: NVIDIA Corporation
License: Other/Proprietary License (NVIDIA Proprietary Software)
Classifier: Intended Audience :: Developers
Classifier: Programming Language :: Python
Classifier: Programming Language :: Python :: 3.10
Classifier: Programming Language :: Python :: 3.11
Classifier: Programming Language :: Python :: 3.12
Project-URL: Homepage, https://github.com/nvidia/cuEquivariance
Project-URL: Documentation, https://github.com/nvidia/cuEquivariance
Requires-Python: >=3.10
Requires-Dist: cuequivariance-ops-cu11==0.5.1
Requires-Dist: scipy
Requires-Dist: torch>=2.4; extra == "test"
Requires-Dist: numpy<2.0a0,>=1.23; extra == "test"
Requires-Dist: pytest; extra == "test"
Requires-Dist: onnx; extra == "plugins"
Requires-Dist: onnxscript; extra == "plugins"
Requires-Dist: onnxruntime; extra == "plugins"
Requires-Dist: onnxruntime-extensions; extra == "plugins"
Requires-Dist: tensorrt-cu11; extra == "plugins"
Requires-Dist: cupy-cuda11x; extra == "plugins"
Requires-Dist: polygraphy; extra == "plugins"
Provides-Extra: test
Provides-Extra: plugins
